README.rst
requirements.txt
setup.py
tensorfx/__init__.py
tensorfx.egg-info/PKG-INFO
tensorfx.egg-info/SOURCES.txt
tensorfx.egg-info/dependency_links.txt
tensorfx.egg-info/requires.txt
tensorfx.egg-info/top_level.txt
tensorfx/data/__init__.py
tensorfx/data/_dataset.py
tensorfx/data/_ds_csv.py
tensorfx/data/_ds_df.py
tensorfx/data/_features.py
tensorfx/data/_metadata.py
tensorfx/data/_schema.py
tensorfx/data/_transforms.py
tensorfx/models/__init__.py
tensorfx/models/_classification.py
tensorfx/models/nn/__init__.py
tensorfx/models/nn/_ff.py
tensorfx/prediction/__init__.py
tensorfx/prediction/_model.py
tensorfx/tools/__init__.py
tensorfx/tools/train.py
tensorfx/training/__init__.py
tensorfx/training/_args.py
tensorfx/training/_config.py
tensorfx/training/_hooks.py
tensorfx/training/_job.py
tensorfx/training/_model.py
tensorfx/training/_trainer.py