Metadata-Version: 1.0
Name: tensorfx
Version: 0.1.3
Summary: TensorFX Framework
Home-page: https://github.com/TensorLab/tensorfx
Author: Nikhil Kothari
Author-email: nikhilk@twitter
License: Apache Software License
Keywords: TensorLab,TensorFlow,Machine Learning,Deep Learning,Google
Platform: UNKNOWN
